Metadata-Version: 1.0
Name: jaim-probability
Version: 0.1
Summary: Gaussian and Binomial distributions
Home-page: UNKNOWN
Author: José Imedio
Author-email: sofake@email.com
License: UNKNOWN
Platform: UNKNOWN
